windows_rs_mcp/__init__.py
windows_rs_mcp/browser_manager.py
windows_rs_mcp/cache.py
windows_rs_mcp/config.py
windows_rs_mcp/docs.py
windows_rs_mcp/scraper.py
windows_rs_mcp/search_index.py
windows_rs_mcp/service.py
windows_rs_mcp-0.4.0.dist-info/METADATA
windows_rs_mcp-0.4.0.dist-info/WHEEL
windows_rs_mcp-0.4.0.dist-info/entry_points.txt
windows_rs_mcp-0.4.0.dist-info/licenses/LICENSE
windows_rs_mcp-0.4.0.dist-info/RECORD
