Metadata-Version: 2.4
Name: windows-rs-mcp
Version: 0.4.0
Summary: MCP server to parse documentation for the windows crate
Author-email: Matt Hand <matterpreter@users.noreply.github.com>, Max Harley <t94j0@users.noreply.github.com>
License-File: LICENSE
Requires-Python: >=3.12
Requires-Dist: httpx>=0.27.0
Requires-Dist: mcp[cli]>=1.16.0
Requires-Dist: playwright>=1.55.0
